airflow/providers/rabbitmq/__init__.py
airflow/providers/rabbitmq/provider.yaml
airflow/providers/rabbitmq/version.py
airflow/providers/rabbitmq/hooks/__init__.py
airflow/providers/rabbitmq/hooks/rabbitmq_hook.py
airflow/providers/rabbitmq/operators/__init__.py
airflow/providers/rabbitmq/operators/rabbitmq_producer.py
airflow/providers/rabbitmq/sensors/__init__.py
airflow/providers/rabbitmq/sensors/rabbitmq_sensor.py
apache_airflow_provider_rabbitmq-2.0.0.dist-info/METADATA
apache_airflow_provider_rabbitmq-2.0.0.dist-info/WHEEL
apache_airflow_provider_rabbitmq-2.0.0.dist-info/licenses/LICENSE
apache_airflow_provider_rabbitmq-2.0.0.dist-info/RECORD
