Metadata-Version: 2.4
Name: apache-airflow-provider-rabbitmq
Version: 2.0.0
Summary: Airflow provider for RabbitMQ with sync/async messaging.
Author-email: Mustafa Abuelfadl <mustafa@zidan.me>
License:                                  Apache License
License-File: LICENSE
Requires-Python: >=3.12
Requires-Dist: aio-pika<10.0.0,>=9.5.0
Requires-Dist: apache-airflow>=3.0.0
Requires-Dist: pika<2.0.0,>=1.3.0
Provides-Extra: development
Requires-Dist: black<24.0.0,>=23.0.0; extra == 'development'
Requires-Dist: flake8<8.0.0,>=7.2.0; extra == 'development'
Requires-Dist: isort<6.0.0,>=5.0.0; extra == 'development'
Requires-Dist: mypy<2.0.0,>=1.0.0; extra == 'development'
Requires-Dist: pylint<4.0.0,>=3.0.0; extra == 'development'
Requires-Dist: pytest-asyncio<1.0.0,>=0.23.0; extra == 'development'
Requires-Dist: pytest-cov<5.0.0,>=4.0.0; extra == 'development'
Requires-Dist: pytest<8.0.0,>=7.0.0; extra == 'development'
Requires-Dist: testcontainers>=4.9.2; extra == 'development'
